gyptis/__about__.py
gyptis/__init__.py
gyptis/api.py
gyptis/bc.py
gyptis/complex.py
gyptis/materials.py
gyptis/measure.py
gyptis/optimize.py
gyptis/plot.py
gyptis/subdomain.cpp
gyptis/formulations/__init__.py
gyptis/formulations/_high_contrast.py
gyptis/formulations/formulation.py
gyptis/formulations/maxwell2d.py
gyptis/formulations/maxwell2dbands.py
gyptis/formulations/maxwell2dperiodic.py
gyptis/formulations/maxwell3d.py
gyptis/formulations/maxwell3dbands.py
gyptis/formulations/maxwell3dperiodic.py
gyptis/formulations/maxwellguided2d.py
gyptis/formulations/twoscale2d.py
gyptis/formulations/twoscale3d.py
gyptis/geometry/__init__.py
gyptis/geometry/geometry.py
gyptis/geometry/grating2d.py
gyptis/geometry/grating3d.py
gyptis/geometry/phc2d.py
gyptis/geometry/phc3d.py
gyptis/geometry/scattering2d.py
gyptis/geometry/scattering3d.py
gyptis/mesh/__init__.py
gyptis/mesh/_submesh.py
gyptis/mesh/mesh.py
gyptis/models/__init__.py
gyptis/models/grating2d.py
gyptis/models/grating3d.py
gyptis/models/hc2d.py
gyptis/models/metaclasses.py
gyptis/models/phc2d.py
gyptis/models/phc3d.py
gyptis/models/phcfibersconical.py
gyptis/models/scattering2d.py
gyptis/models/scattering3d.py
gyptis/models/simulation.py
gyptis/models/twoscale2d.py
gyptis/models/twoscale3d.py
gyptis/models/waveguide2d.py
gyptis/sources/__init__.py
gyptis/sources/dipole.py
gyptis/sources/gaussian.py
gyptis/sources/ls.py
gyptis/sources/pw.py
gyptis/sources/source.py
gyptis/sources/spharm.py
gyptis/sources/stack.py
gyptis/utils/__init__.py
gyptis/utils/bands.py
gyptis/utils/data_download.py
gyptis/utils/helpers.py
gyptis/utils/jupyter.py
gyptis/utils/log.py
gyptis/utils/parallel.py
gyptis/utils/sample.py
gyptis/utils/time.py
gyptis-1.1.2.dist-info/licenses/LICENSE.txt
gyptis-1.1.2.dist-info/METADATA
gyptis-1.1.2.dist-info/WHEEL
gyptis-1.1.2.dist-info/top_level.txt
gyptis-1.1.2.dist-info/RECORD
