Metadata-Version: 2.4
Name: gyptis
Version: 1.1.2
Summary: Computational Photonics in Python
Home-page: https://gitlab.com/gyptis/gyptis
Author: Benjamin Vial
License: MIT
Project-URL: Code, https://gitlab.com/gyptis/gyptis
Project-URL: Documentation, https://gyptis.gitlab.io
Project-URL: Issues, https://gitlab.com/gyptis/gyptis/issues
Keywords: finite element method,diffraction,scattering,optics,photonics,metamaterials,modal analysis
Classifier: Development Status :: 5 - Production/Stable
Classifier: Intended Audience :: Science/Research
Classifier: Operating System :: OS Independent
Classifier: Programming Language :: Python
Classifier: Programming Language :: Python :: 3
Classifier: Programming Language :: Python :: 3.10
Classifier: Programming Language :: Python :: 3.11
Classifier: Programming Language :: Python :: 3.12
Classifier: Programming Language :: Python :: 3.13
Classifier: Programming Language :: Python :: 3.14
Classifier: Topic :: Scientific/Engineering
Classifier: Topic :: Scientific/Engineering :: Mathematics
Classifier: Topic :: Scientific/Engineering :: Physics
Requires-Python: >=3.10
License-File: LICENSE.txt
Requires-Dist: numpy
Requires-Dist: scipy
Requires-Dist: matplotlib
Requires-Dist: pyvista
Requires-Dist: sympy
Requires-Dist: dolfin-adjoint
Requires-Dist: meshio
Requires-Dist: joblib
Requires-Dist: psutil
Requires-Dist: ipython
Requires-Dist: loguru
Provides-Extra: mesh
Requires-Dist: gmsh; extra == "mesh"
Provides-Extra: opt
Requires-Dist: nlopt; extra == "opt"
Provides-Extra: full
Requires-Dist: gyptis[mesh]; extra == "full"
Requires-Dist: gyptis[opt]; extra == "full"
Dynamic: license-file
